afam/__init__.py
afam/asc_dataset.py
afam/asc_event.py
afam/asc_sample.py
afam-0.1.1.dist-info/LICENSE
afam-0.1.1.dist-info/WHEEL
afam-0.1.1.dist-info/METADATA
afam-0.1.1.dist-info/RECORD
