Metadata-Version: 2.1
Name: afam
Version: 0.1.1
Summary: ASC Files Analyzing Module
License: GNU General Public License v3.0
Author: Christoph Anzengruber
Requires-Python: >=3.7.9,<4.0
Classifier: License :: Other/Proprietary License
Classifier: Programming Language :: Python :: 3
Classifier: Programming Language :: Python :: 3.8
Classifier: Programming Language :: Python :: 3.9
Classifier: Programming Language :: Python :: 3.10
Classifier: Programming Language :: Python :: 3.11
Requires-Dist: pandas (>=1.3.5,<2.0.0)
Requires-Dist: scipy (>=1.7.3,<2.0.0)
